pdql/__init__.py
pdql/dataframe.py
pdql/dialects.py
pdql/expressions.py
pdql/functions/__init__.py
pdql/functions/aggregate.py
pdql/functions/array.py
pdql/functions/crypto.py
pdql/functions/datetime.py
pdql/functions/geography.py
pdql/functions/json.py
pdql/functions/math.py
pdql/functions/net.py
pdql/functions/string.py
pdql-0.2.0.dist-info/METADATA
pdql-0.2.0.dist-info/WHEEL
pdql-0.2.0.dist-info/licenses/LICENSE.md
pdql-0.2.0.dist-info/RECORD
