Metadata-Version: 2.4
Name: pdql
Version: 0.2.0
Summary: A library to transpile Pandas syntax to SQL strings.
Project-URL: Homepage, https://github.com/marcinz606/pdql
Project-URL: Issues, https://github.com/marcinz606/pdql/issues
Author-email: Marcin Zawalski <zawalskimarcin@gmail.com>
License: MIT
License-File: LICENSE.md
Classifier: License :: OSI Approved :: MIT License
Classifier: Operating System :: OS Independent
Classifier: Programming Language :: Python :: 3
Requires-Python: >=3.8
Provides-Extra: dev
Requires-Dist: flake8; extra == 'dev'
Requires-Dist: mypy; extra == 'dev'
Requires-Dist: pytest; extra == 'dev'
Requires-Dist: ruff; extra == 'dev'
